k3httpmultipart/__init__.py
k3httpmultipart/multipart.py
k3httpmultipart/synopsis.py
k3httpmultipart-0.1.4.dist-info/licenses/LICENSE
k3httpmultipart-0.1.4.dist-info/METADATA
k3httpmultipart-0.1.4.dist-info/WHEEL
k3httpmultipart-0.1.4.dist-info/top_level.txt
k3httpmultipart-0.1.4.dist-info/RECORD
